[
  { "id": 1, "title": "Free Pizza & Resume Review", "org": "SCP", "category": "career", "tags": ["free food", "networking", "career", "resume"], "date": "2026-04-11", "time": "18:00", "location": "Marshall Center 2301", "description": "Drop in for free pizza while SCP members review your resume and give feedback.", "capacity": 40, "registered": 12 },
  { "id": 2, "title": "Intro to Machine Learning Workshop", "org": "ACM", "category": "tech", "tags": ["AI", "machine learning", "workshop", "coding"], "date": "2026-04-12", "time": "14:00", "location": "ENB 118", "description": "Beginner-friendly workshop covering supervised learning fundamentals with Python.", "capacity": 60, "registered": 45 },
  { "id": 3, "title": "Yoga on the Lawn", "org": "Campus Recreation", "category": "wellness", "tags": ["yoga", "fitness", "outdoor", "relaxation"], "date": "2026-04-10", "time": "08:00", "location": "MLK Plaza", "description": "Start your morning with a guided yoga session on the lawn. All levels welcome.", "capacity": 30, "registered": 28 },
  { "id": 4, "title": "Hackathon Prep Night", "org": "SCP", "category": "tech", "tags": ["hackathon", "coding", "prep", "team building"], "date": "2026-04-13", "time": "19:00", "location": "Library Room 218", "description": "Form teams and brainstorm project ideas for the upcoming HackaBull hackathon.", "capacity": 50, "registered": 50 },
  { "id": 5, "title": "Bulls Basketball Watch Party", "org": "Student Government", "category": "sports", "tags": ["basketball", "watch party", "social", "free food"], "date": "2026-04-14", "time": "20:00", "location": "Marshall Center Ballroom", "description": "Watch the Bulls play on the big screen with free wings and drinks.", "capacity": 200, "registered": 134 },
  { "id": 6, "title": "Mindfulness Meditation Session", "org": "Counseling Center", "category": "wellness", "tags": ["meditation", "mental health", "stress relief", "relaxation"], "date": "2026-04-11", "time": "12:00", "location": "SVC 2054", "description": "A 30-minute guided meditation to help manage stress during midterms.", "capacity": 25, "registered": 10 },
  { "id": 7, "title": "Career Fair: Engineering & Tech", "org": "Career Services", "category": "career", "tags": ["career fair", "engineering", "tech", "internship", "jobs"], "date": "2026-04-15", "time": "10:00", "location": "Sun Dome", "description": "Meet recruiters from top tech companies. Bring your resume and dress professionally.", "capacity": 500, "registered": 312 },
  { "id": 8, "title": "D&D One-Shot Night", "org": "Tabletop Gaming Club", "category": "social", "tags": ["dungeons and dragons", "tabletop", "gaming", "social"], "date": "2026-04-11", "time": "18:30", "location": "MSC 3707", "description": "Join us for a beginner-friendly one-shot adventure. No experience needed, characters provided.", "capacity": 20, "registered": 16 },
  { "id": 9, "title": "Python for Data Science", "org": "Data Science Club", "category": "tech", "tags": ["python", "data science", "workshop", "coding", "pandas"], "date": "2026-04-12", "time": "16:00", "location": "ISA 1051", "description": "Hands-on workshop using pandas and matplotlib for data analysis.", "capacity": 40, "registered": 38 },
  { "id": 10, "title": "Intramural Soccer Signups", "org": "Campus Recreation", "category": "sports", "tags": ["soccer", "intramural", "sports", "team"], "date": "2026-04-09", "time": "17:00", "location": "Rec Center Lobby", "description": "Last day to sign up for spring intramural soccer leagues.", "capacity": 100, "registered": 100 },
  { "id": 11, "title": "Study Abroad Info Session", "org": "Education Abroad", "category": "academic", "tags": ["study abroad", "travel", "academic", "international"], "date": "2026-04-14", "time": "13:00", "location": "CGS 109", "description": "Learn about summer and fall study abroad programs and scholarship opportunities.", "capacity": 35, "registered": 8 },
  { "id": 12, "title": "Open Mic Night", "org": "Bulls Radio", "category": "social", "tags": ["music", "open mic", "performance", "social", "art"], "date": "2026-04-12", "time": "20:00", "location": "The Oval Theater", "description": "Sign up to perform or just come enjoy live music, poetry, and comedy.", "capacity": 80, "registered": 42 },
  { "id": 13, "title": "GRE Prep Workshop", "org": "Graduate School", "category": "academic", "tags": ["GRE", "grad school", "test prep", "academic"], "date": "2026-04-16", "time": "15:00", "location": "Library Room 120", "description": "Strategies and practice for the GRE quantitative and verbal sections.", "capacity": 30, "registered": 22 },
  { "id": 14, "title": "Free Smoothie Monday", "org": "Student Government", "category": "social", "tags": ["free food", "smoothie", "social", "monday"], "date": "2026-04-07", "time": "11:00", "location": "Cooper Hall Lobby", "description": "Grab a free smoothie to start your week right. First 100 students only.", "capacity": 100, "registered": 100 },
  { "id": 15, "title": "Cybersecurity CTF Competition", "org": "Whitehatters", "category": "tech", "tags": ["cybersecurity", "CTF", "hacking", "competition", "coding"], "date": "2026-04-18", "time": "10:00", "location": "ENB 313", "description": "Capture-the-flag competition. Test your skills in web exploitation, crypto, and forensics.", "capacity": 60, "registered": 35 },
  { "id": 16, "title": "Financial Literacy 101", "org": "Business LLC", "category": "career", "tags": ["finance", "budgeting", "personal finance", "workshop"], "date": "2026-04-11", "time": "15:00", "location": "BSN 115", "description": "Learn budgeting, saving, and investing basics. Free workbook included.", "capacity": 45, "registered": 19 },
  { "id": 17, "title": "Rock Climbing Night", "org": "Campus Recreation", "category": "sports", "tags": ["rock climbing", "fitness", "adventure", "social"], "date": "2026-04-13", "time": "19:00", "location": "Rec Center Wall", "description": "Free belay instruction and climbing for all skill levels.", "capacity": 25, "registered": 18 },
  { "id": 18, "title": "Research Symposium Poster Session", "org": "Office of Research", "category": "academic", "tags": ["research", "poster", "academic", "undergraduate"], "date": "2026-04-17", "time": "09:00", "location": "Marshall Center Ballroom", "description": "Undergraduate and graduate students present their research posters.", "capacity": 200, "registered": 156 },
  { "id": 19, "title": "International Food Festival", "org": "International Student Org", "category": "social", "tags": ["food", "free food", "international", "culture", "social"], "date": "2026-04-16", "time": "17:00", "location": "MLK Plaza", "description": "Taste dishes from around the world prepared by international student organizations.", "capacity": 300, "registered": 189 },
  { "id": 20, "title": "AWS Cloud Workshop", "org": "ACM", "category": "tech", "tags": ["AWS", "cloud", "workshop", "coding", "devops"], "date": "2026-04-19", "time": "13:00", "location": "ENB 118", "description": "Deploy your first app on AWS. Covers EC2, S3, and Lambda basics.", "capacity": 40, "registered": 29 },
  { "id": 21, "title": "Movie Night: Interstellar", "org": "Campus Activities Board", "category": "social", "tags": ["movie", "social", "free", "entertainment"], "date": "2026-04-12", "time": "21:00", "location": "MSC Oval Theater", "description": "Free outdoor screening of Interstellar. Blankets and popcorn provided.", "capacity": 150, "registered": 88 },
  { "id": 22, "title": "Women in STEM Panel", "org": "Society of Women Engineers", "category": "career", "tags": ["women in STEM", "panel", "career", "networking", "diversity"], "date": "2026-04-14", "time": "16:00", "location": "ENG 3", "description": "Hear from women leaders in engineering, CS, and data science about their career journeys.", "capacity": 70, "registered": 52 },
  { "id": 23, "title": "Volunteer at Feeding Tampa Bay", "org": "Center for Leadership", "category": "social", "tags": ["volunteer", "community service", "food bank", "social good"], "date": "2026-04-15", "time": "08:00", "location": "Off Campus (Bus Provided)", "description": "Help sort and pack food for families in need. Transportation included.", "capacity": 30, "registered": 24 },
  { "id": 24, "title": "Leetcode Study Group", "org": "SCP", "category": "tech", "tags": ["leetcode", "coding", "algorithms", "interview prep", "DSA"], "date": "2026-04-11", "time": "17:00", "location": "Library Room 210", "description": "Weekly problem-solving session. This week: dynamic programming patterns.", "capacity": 20, "registered": 14 },
  { "id": 25, "title": "Salsa Dancing Social", "org": "Latin Dance Club", "category": "social", "tags": ["dance", "salsa", "social", "latin", "music"], "date": "2026-04-13", "time": "20:00", "location": "MSC Ballroom B", "description": "Beginner lesson at 8pm, open social dancing at 9pm. No partner needed.", "capacity": 60, "registered": 33 },
  { "id": 26, "title": "Pre-Med Advising Drop-In", "org": "Pre-Health Advising", "category": "academic", "tags": ["pre-med", "advising", "medical school", "academic"], "date": "2026-04-10", "time": "14:00", "location": "SVC 1056", "description": "Get your questions answered about MCAT prep, clinical hours, and applications.", "capacity": 15, "registered": 15 },
  { "id": 27, "title": "Startup Pitch Night", "org": "Entrepreneurship Club", "category": "career", "tags": ["startup", "pitch", "entrepreneurship", "business", "networking"], "date": "2026-04-17", "time": "18:00", "location": "Muma Business Building 1200", "description": "Watch student teams pitch their startup ideas to a panel of investors and mentors.", "capacity": 80, "registered": 61 },
  { "id": 28, "title": "Bob Ross Paint Night", "org": "Campus Activities Board", "category": "social", "tags": ["art", "painting", "social", "creative", "relaxation"], "date": "2026-04-15", "time": "19:00", "location": "MSC 3707", "description": "Follow along to a Bob Ross tutorial. All supplies provided. Happy little trees!", "capacity": 30, "registered": 30 },
  { "id": 29, "title": "Linux Command Line Bootcamp", "org": "ACM", "category": "tech", "tags": ["linux", "command line", "terminal", "workshop", "coding"], "date": "2026-04-18", "time": "15:00", "location": "ENB 118", "description": "Learn essential bash commands, file navigation, and shell scripting basics.", "capacity": 35, "registered": 21 },
  { "id": 30, "title": "Campus 5K Fun Run", "org": "Campus Recreation", "category": "sports", "tags": ["running", "5K", "fitness", "outdoor", "fun run"], "date": "2026-04-19", "time": "07:30", "location": "Alumni Drive", "description": "A casual 5K around campus. Free t-shirt for all finishers. No registration fee.", "capacity": 150, "registered": 97 },
  { "id": 31, "title": "Origami Workshop", "org": "Japanese Culture Club", "category": "social", "tags": ["origami", "art", "craft", "Japanese", "culture"], "date": "2026-04-13", "time": "14:00", "location": "MSC 2708", "description": "Learn to fold cranes, flowers, and more. All materials provided.", "capacity": 25, "registered": 11 },
  { "id": 32, "title": "Therapy Dog Visit", "org": "Counseling Center", "category": "wellness", "tags": ["therapy dogs", "stress relief", "mental health", "animals"], "date": "2026-04-16", "time": "11:00", "location": "Library Lawn", "description": "Pet therapy dogs during midterms week. Sponsored by the Counseling Center.", "capacity": 999, "registered": 0 },
  { "id": 33, "title": "Competitive Programming Practice", "org": "SCP", "category": "tech", "tags": ["competitive programming", "algorithms", "coding", "ICPC"], "date": "2026-04-14", "time": "18:00", "location": "ENB 313", "description": "Practice ICPC-style problems. This week's focus: graph algorithms.", "capacity": 30, "registered": 17 },
  { "id": 34, "title": "Sunset Kayaking Trip", "org": "Outdoor Adventures", "category": "sports", "tags": ["kayaking", "outdoor", "adventure", "nature", "social"], "date": "2026-04-18", "time": "17:30", "location": "Riverfront Park (Off Campus)", "description": "Paddle along the Hillsborough River at sunset. Equipment and transport provided.", "capacity": 16, "registered": 16 },
  { "id": 35, "title": "Ethics in AI Panel Discussion", "org": "Philosophy Club", "category": "academic", "tags": ["AI", "ethics", "panel", "philosophy", "discussion"], "date": "2026-04-17", "time": "16:00", "location": "FAO 101", "description": "Faculty panel on bias in machine learning, autonomous weapons, and AI governance.", "capacity": 50, "registered": 27 },
  { "id": 36, "title": "Chess Tournament", "org": "Chess Club", "category": "social", "tags": ["chess", "tournament", "competition", "strategy"], "date": "2026-04-19", "time": "12:00", "location": "MSC Game Room", "description": "Swiss-system tournament. All skill levels welcome. Prizes for top 3.", "capacity": 32, "registered": 28 },
  { "id": 37, "title": "Resume Writing Workshop", "org": "Career Services", "category": "career", "tags": ["resume", "career", "workshop", "job search"], "date": "2026-04-10", "time": "13:00", "location": "SVC 1072", "description": "Learn how to write a standout resume that gets past ATS systems.", "capacity": 30, "registered": 30 },
  { "id": 38, "title": "Plant Swap & Care Tips", "org": "Botany Club", "category": "social", "tags": ["plants", "swap", "gardening", "social", "nature"], "date": "2026-04-12", "time": "11:00", "location": "Botanical Garden Pavilion", "description": "Bring a plant cutting to trade. Learn care tips from botany students.", "capacity": 40, "registered": 22 },
  { "id": 39, "title": "Grad School Application Workshop", "org": "Graduate School", "category": "academic", "tags": ["grad school", "application", "academic", "personal statement"], "date": "2026-04-15", "time": "14:00", "location": "Library Room 120", "description": "How to write a strong personal statement and secure recommendation letters.", "capacity": 25, "registered": 18 },
  { "id": 40, "title": "Spikeball Tournament", "org": "Campus Recreation", "category": "sports", "tags": ["spikeball", "tournament", "outdoor", "sports", "social"], "date": "2026-04-13", "time": "15:00", "location": "Castor Beach", "description": "2v2 spikeball tournament. Sign up as a pair. Prizes for winning team.", "capacity": 24, "registered": 20 },
  { "id": 41, "title": "Intro to Figma for Developers", "org": "ACM", "category": "tech", "tags": ["figma", "design", "UI/UX", "workshop"], "date": "2026-04-16", "time": "15:00", "location": "ENB 118", "description": "Learn Figma basics: auto-layout, components, and developer handoff.", "capacity": 35, "registered": 26 },
  { "id": 42, "title": "Trivia Night", "org": "Campus Activities Board", "category": "social", "tags": ["trivia", "social", "competition", "fun", "team"], "date": "2026-04-11", "time": "20:00", "location": "MSC Oval Theater", "description": "Teams of up to 6. Categories include pop culture, science, and USF history.", "capacity": 120, "registered": 78 },
  { "id": 43, "title": "Mock Interview Day", "org": "Career Services", "category": "career", "tags": ["interview", "career", "practice", "mock interview", "job search"], "date": "2026-04-18", "time": "09:00", "location": "SVC 1072", "description": "Practice behavioral and technical interviews with industry professionals.", "capacity": 40, "registered": 36 },
  { "id": 44, "title": "Astronomy Observation Night", "org": "Physics Club", "category": "academic", "tags": ["astronomy", "stars", "telescope", "science", "outdoor"], "date": "2026-04-17", "time": "21:00", "location": "Science Center Roof", "description": "View Jupiter and its moons through the department telescope. Weather permitting.", "capacity": 20, "registered": 13 },
  { "id": 45, "title": "Board Game Cafe Night", "org": "Tabletop Gaming Club", "category": "social", "tags": ["board games", "social", "gaming", "cafe"], "date": "2026-04-14", "time": "19:00", "location": "MSC 3707", "description": "Play Catan, Wingspan, Ticket to Ride, and more. Snacks and drinks provided.", "capacity": 30, "registered": 21 },
  { "id": 46, "title": "CPR & First Aid Certification", "org": "Campus Recreation", "category": "wellness", "tags": ["CPR", "first aid", "certification", "safety", "training"], "date": "2026-04-19", "time": "09:00", "location": "Rec Center Room 203", "description": "Get American Red Cross CPR and First Aid certified. $25 materials fee.", "capacity": 20, "registered": 17 },
  { "id": 47, "title": "GitHub & Git Workshop", "org": "SCP", "category": "tech", "tags": ["git", "github", "version control", "workshop", "coding"], "date": "2026-04-10", "time": "16:00", "location": "Library Room 218", "description": "Learn branching, merging, pull requests, and collaborative workflows.", "capacity": 30, "registered": 23 },
  { "id": 48, "title": "Spoken Word Poetry Slam", "org": "Creative Writing Club", "category": "social", "tags": ["poetry", "spoken word", "performance", "art", "social"], "date": "2026-04-16", "time": "19:30", "location": "Oval Theater", "description": "Share original work or come listen. Theme: 'What Keeps You Up at Night.'", "capacity": 50, "registered": 31 },
  { "id": 49, "title": "Nutrition & Meal Prep on a Budget", "org": "Student Health", "category": "wellness", "tags": ["nutrition", "meal prep", "health", "budget", "cooking"], "date": "2026-04-14", "time": "12:00", "location": "MSC Kitchen", "description": "Learn to plan and prep healthy meals for under $30/week.", "capacity": 20, "registered": 18 },
  { "id": 50, "title": "Capture the Flag: Outdoor Edition", "org": "Campus Recreation", "category": "sports", "tags": ["capture the flag", "outdoor", "sports", "team", "fun"], "date": "2026-04-13", "time": "16:00", "location": "Sycamore Fields", "description": "Giant outdoor CTF game. Teams of 10. Free t-shirts for participants.", "capacity": 80, "registered": 54 }
]